akamal/__init__.py
akamal/send_webhook.py
akatest/__init__.py
akatest/send_webhook.py
akatest-0.4.dist-info/METADATA
akatest-0.4.dist-info/WHEEL
akatest-0.4.dist-info/entry_points.txt
akatest-0.4.dist-info/top_level.txt
akatest-0.4.dist-info/RECORD
