Metadata-Version: 2.1
Name: akatest
Version: 0.4
Summary: A simple package to send a webhook request to a URL
Home-page: https://github.com/noama163/akatest
Author: Your Name
Author-email: your_email@example.com
License: UNKNOWN
Platform: UNKNOWN
Classifier: Programming Language :: Python :: 3
Classifier: License :: OSI Approved :: MIT License
Classifier: Operating System :: OS Independent
Requires-Python: >=3.6
